<?xml version="1.0" encoding="utf-8"?>
<Technology xmlns:xsi="http://www.w3.org/2001/XMLSchema-instance" xmlns:xsd="http://www.w3.org/2001/ XMLSchema"> 
  <Version>2</Version>
  <UID>AssaultCannonType81</UID>
  <TechnologyType>ShipWeapons</TechnologyType>
  <Cost>4560</Cost>
  <NameIndex>18846</NameIndex>
  <DescriptionIndex>18847</DescriptionIndex>
  <ModulesUnlocked>
    <UnlockedMod>
      <ModuleUID>Assault_Cannon_Type81</ModuleUID>
    </UnlockedMod>
  </ModulesUnlocked>
  <BuildingsUnlocked />
  <BonusUnlocked />
  <TroopsUnlocked />
  <HullsUnlocked />
</Technology>
